README.md
setup.py
src/injection_mold.egg-info/PKG-INFO
src/injection_mold.egg-info/SOURCES.txt
src/injection_mold.egg-info/dependency_links.txt
src/injection_mold.egg-info/requires.txt
src/injection_mold.egg-info/top_level.txt
src/mold/__init__.py
src/mold/annotations.py
src/mold/bean.py
src/mold/bean_context.py
src/mold/bean_registry.py
src/mold/container.py
src/mold/event_registry.py
src/mold/scanner.py
src/mold/type_dict.py
src/mold/util.py
test/test_event_handler.py
test/test_inject.py
test/test_registry.py
test/test_type_dict.py