Metadata-Version: 2.1
Name: injection-mold
Version: 0.0.1
Summary: Spring/Micronaut-esque dependency injection system for Python using type hints
Home-page: https://github.com/jmccaffrey42/mold
Author: Jonathan McCaffrey
Author-email: jmc@teammccaffrey.com
License: MPL-2.0
Platform: UNKNOWN
Classifier: Development Status :: 3 - Alpha
Classifier: Programming Language :: Python :: 3.6
